MutatorMath-2.1.1.dist-info/LICENSE.txt
MutatorMath-2.1.1.dist-info/METADATA
MutatorMath-2.1.1.dist-info/RECORD
MutatorMath-2.1.1.dist-info/WHEEL
MutatorMath-2.1.1.dist-info/top_level.txt
mutatorMath/__init__.py
mutatorMath/objects/__init__.py
mutatorMath/objects/bender.py
mutatorMath/objects/error.py
mutatorMath/objects/location.py
mutatorMath/objects/mutator.py
mutatorMath/ufo/__init__.py
mutatorMath/ufo/document.py
mutatorMath/ufo/instance.py
