Metadata-Version: 2.1
Name: MutatorMath
Version: 2.1.1
Summary: Python for piecewise linear interpolation in multiple dimensions with multiple, arbitrarily placed, masters.
Home-page: https://github.com/LettError/MutatorMath
Author: Erik van Blokland
Author-email: erik@letterror.com
License: BSD 3 Clause
Platform: UNKNOWN
Classifier: Development Status :: 5 - Production/Stable
Classifier: Environment :: Console
Classifier: Environment :: Other Environment
Classifier: Intended Audience :: Developers
Classifier: Intended Audience :: End Users/Desktop
Classifier: License :: OSI Approved :: BSD License
Classifier: Natural Language :: English
Classifier: Operating System :: OS Independent
Classifier: Programming Language :: Python
Classifier: Programming Language :: Python :: 2
Classifier: Programming Language :: Python :: 3
Classifier: Topic :: Multimedia :: Graphics
Classifier: Topic :: Multimedia :: Graphics :: Graphics Conversion
Classifier: Topic :: Multimedia :: Graphics :: Editors :: Vector-Based
Classifier: Topic :: Software Development :: Libraries :: Python Modules
Requires-Dist: ufoLib (>=2.0.0)
Requires-Dist: defcon (>=0.3.5)
Requires-Dist: fontMath (>=0.4.4)
